{
    "configurations": [
        {
            "name": "Mac",
            "includePath": [
                "${workspaceFolder}/**",
                "/opt/homebrew/include/SDL2",
                "/opt/homebrew/lib",
                "/opt/homebrew/include"
            ],
            "browse": {
                "path": [
                    "/opt/homebrew/include/SDL2",
                    "/opt/homebrew/lib"
                ],
                "limitSymbolsToIncludedHeaders": true
            },
            "defines": [],
            "compilerPath": "/usr/bin/clang",
            "cStandard": "c17",
            "cppStandard": "c++17",
            "intelliSenseMode": "macos-clang-arm64"
        }
    ],
    "version": 4
}